[
  {
    "filename": "backup_20251003_163128_auto_1631.zip",
    "path": "backups\\backup_20251003_163128_auto_1631.zip",
    "size": 27573,
    "created_at": "2025-10-03T16:31:28.731419",
    "comment": "auto_1631",
    "file_count": 5
  },
  {
    "filename": "backup_20251003_164434_auto_1644.zip",
    "path": "backups\\backup_20251003_164434_auto_1644.zip",
    "size": 28139,
    "created_at": "2025-10-03T16:44:34.539789",
    "comment": "auto_1644",
    "file_count": 5
  },
  {
    "filename": "backup_20251003_165039_auto_1650.zip",
    "path": "backups\\backup_20251003_165039_auto_1650.zip",
    "size": 28330,
    "created_at": "2025-10-03T16:50:39.829097",
    "comment": "auto_1650",
    "file_count": 5
  },
  {
    "filename": "backup_20251003_170049_auto_1700.zip",
    "path": "backups\\backup_20251003_170049_auto_1700.zip",
    "size": 28592,
    "created_at": "2025-10-03T17:00:49.380073",
    "comment": "auto_1700",
    "file_count": 5
  },
  {
    "filename": "backup_20251003_171258_auto_1712.zip",
    "path": "backups\\backup_20251003_171258_auto_1712.zip",
    "size": 28787,
    "created_at": "2025-10-03T17:12:58.440266",
    "comment": "auto_1712",
    "file_count": 5
  },
  {
    "filename": "backup_20251003_172409_auto_1724.zip",
    "path": "backups\\backup_20251003_172409_auto_1724.zip",
    "size": 28935,
    "created_at": "2025-10-03T17:24:09.806508",
    "comment": "auto_1724",
    "file_count": 5
  },
  {
    "filename": "backup_20251006_090908_auto_0909.zip",
    "path": "backups\\backup_20251006_090908_auto_0909.zip",
    "size": 27556,
    "created_at": "2025-10-06T09:09:09.007140",
    "comment": "auto_0909",
    "file_count": 5
  },
  {
    "filename": "backup_20251006_101100_auto_1011.zip",
    "path": "backups\\backup_20251006_101100_auto_1011.zip",
    "size": 27883,
    "created_at": "2025-10-06T10:11:00.318208",
    "comment": "auto_1011",
    "file_count": 5
  },
  {
    "filename": "backup_20251006_152607_auto_1526.zip",
    "path": "backups\\backup_20251006_152607_auto_1526.zip",
    "size": 32682,
    "created_at": "2025-10-06T15:26:07.559727",
    "comment": "auto_1526",
    "file_count": 5
  }
]